missim_config/__init__.py
missim_config/generate_schemas.py
missim_config/launch_parameters.py
missim_config/generated/launch_parameters.py
missim_config/generated/launch_parameters.schema.json
missim_config/schemas/missim.schema.json
missim_config/test/missim_config_test.py
missim_config-2.0.0.dist-info/METADATA
missim_config-2.0.0.dist-info/WHEEL
missim_config-2.0.0.dist-info/top_level.txt
missim_config-2.0.0.dist-info/zip-safe
missim_config-2.0.0.dist-info/RECORD
