Metadata-Version: 2.4
Name: missim_config
Version: 2.0.0
Summary: A library for reading / writing Missim config files
Home-page: https://github.com/Greenroom-Robotics/missim
Author: Greenroom Robotics
Author-email: team@greenroomrobotics.com
Maintainer: David Revay
Maintainer-email: david.revay@greenroomrobotics.com
License: Copyright (C) 2023, Greenroom Robotics
Keywords: colcon
Classifier: Development Status :: 3 - Alpha
Classifier: Environment :: Plugins
Classifier: Intended Audience :: Developers
Classifier: Programming Language :: Python
Classifier: Topic :: Software Development :: Build Tools
Requires-Dist: setuptools
Requires-Dist: dacite
Requires-Dist: PyYAML
Requires-Dist: dc-schema
